collective.futures-0.9.3-py2.7-nspkg.pth
collective/futures/__init__.py
collective/futures/adapters.py
collective/futures/api.py
collective/futures/configure.zcml
collective/futures/exceptions.py
collective/futures/interfaces.py
collective/futures/iterators.py
collective/futures/testing.py
collective/futures/transforms.py
collective/futures/tests/__init__.py
collective/futures/tests/test_acceptance.pt
collective/futures/tests/test_acceptance.py
collective/futures/tests/test_acceptance.robot
collective/futures/tests/test_acceptance.zcml
collective.futures-0.9.3.dist-info/DESCRIPTION.rst
collective.futures-0.9.3.dist-info/METADATA
collective.futures-0.9.3.dist-info/RECORD
collective.futures-0.9.3.dist-info/WHEEL
collective.futures-0.9.3.dist-info/entry_points.txt
collective.futures-0.9.3.dist-info/metadata.json
collective.futures-0.9.3.dist-info/namespace_packages.txt
collective.futures-0.9.3.dist-info/top_level.txt
