Metadata-Version: 2.0
Name: collective.futures
Version: 0.9.3
Summary: Experimental non-blocking futures for Plone
Home-page: https://github.com/collective/collective.futures/
Author: Asko Soukka
Author-email: asko.soukka@iki.fi
License: GPL
Platform: UNKNOWN
Classifier: Programming Language :: Python
Classifier: Programming Language :: Python :: 2.7
Classifier: Framework :: Plone :: 4.3
Requires-Dist: setuptools
Requires-Dist: futures
Requires-Dist: Products.CMFPlone
Requires-Dist: zope.globalrequest
Requires-Dist: plone.transformchain
Provides-Extra: test
Requires-Dist: unittest2; extra == 'test'
Requires-Dist: plone.app.testing; extra == 'test'
Requires-Dist: plone.app.robotframework; extra == 'test'
